terminal_shop/__init__.py
terminal_shop/_base_client.py
terminal_shop/_client.py
terminal_shop/_compat.py
terminal_shop/_constants.py
terminal_shop/_exceptions.py
terminal_shop/_files.py
terminal_shop/_models.py
terminal_shop/_qs.py
terminal_shop/_resource.py
terminal_shop/_response.py
terminal_shop/_streaming.py
terminal_shop/_types.py
terminal_shop/_version.py
terminal_shop/py.typed
terminal_shop/_utils/__init__.py
terminal_shop/_utils/_compat.py
terminal_shop/_utils/_datetime_parse.py
terminal_shop/_utils/_json.py
terminal_shop/_utils/_logs.py
terminal_shop/_utils/_proxy.py
terminal_shop/_utils/_reflection.py
terminal_shop/_utils/_resources_proxy.py
terminal_shop/_utils/_streams.py
terminal_shop/_utils/_sync.py
terminal_shop/_utils/_transform.py
terminal_shop/_utils/_typing.py
terminal_shop/_utils/_utils.py
terminal_shop/lib/.keep
terminal_shop/resources/__init__.py
terminal_shop/resources/address.py
terminal_shop/resources/app.py
terminal_shop/resources/card.py
terminal_shop/resources/cart.py
terminal_shop/resources/email.py
terminal_shop/resources/order.py
terminal_shop/resources/product.py
terminal_shop/resources/profile.py
terminal_shop/resources/subscription.py
terminal_shop/resources/token.py
terminal_shop/resources/view.py
terminal_shop/types/__init__.py
terminal_shop/types/address.py
terminal_shop/types/address_create_params.py
terminal_shop/types/address_create_response.py
terminal_shop/types/address_delete_response.py
terminal_shop/types/address_get_response.py
terminal_shop/types/address_list_response.py
terminal_shop/types/app.py
terminal_shop/types/app_create_params.py
terminal_shop/types/app_create_response.py
terminal_shop/types/app_delete_response.py
terminal_shop/types/app_get_response.py
terminal_shop/types/app_list_response.py
terminal_shop/types/card.py
terminal_shop/types/card_collect_response.py
terminal_shop/types/card_create_params.py
terminal_shop/types/card_create_response.py
terminal_shop/types/card_delete_response.py
terminal_shop-1.15.0.dist-info/METADATA
terminal_shop-1.15.0.dist-info/WHEEL
terminal_shop-1.15.0.dist-info/licenses/LICENSE
terminal_shop-1.15.0.dist-info/RECORD
